odoo/addons/stock_picking_return_lot/README.rst
odoo/addons/stock_picking_return_lot/__init__.py
odoo/addons/stock_picking_return_lot/__manifest__.py
odoo/addons/stock_picking_return_lot/i18n/stock_picking_return_lot.pot
odoo/addons/stock_picking_return_lot/readme/CONTRIBUTORS.rst
odoo/addons/stock_picking_return_lot/readme/DESCRIPTION.rst
odoo/addons/stock_picking_return_lot/static/description/icon.png
odoo/addons/stock_picking_return_lot/static/description/index.html
odoo/addons/stock_picking_return_lot/tests/__init__.py
odoo/addons/stock_picking_return_lot/tests/test_stock_picking_return_lot.py
odoo/addons/stock_picking_return_lot/wizard/__init__.py
odoo/addons/stock_picking_return_lot/wizard/stock_picking_return.py
odoo14_addon_stock_picking_return_lot-14.0.1.0.2.dist-info/METADATA
odoo14_addon_stock_picking_return_lot-14.0.1.0.2.dist-info/WHEEL
odoo14_addon_stock_picking_return_lot-14.0.1.0.2.dist-info/top_level.txt
odoo14_addon_stock_picking_return_lot-14.0.1.0.2.dist-info/RECORD
